<xml id="toolbox" style="display: none">

  <category name="Events (when)">

    <block type="touch_start"></block>
    <block type="collision_start"></block>
    <block type="state_entry"></block>
    <block type="object_rez"></block>

  </category>

  <category name="Communication">
    <block type="llsay"></block>
      <block type="llwhisper"></block>
      <block type="llshout"></block>
      <block type="llownersay"></block>
      <block type="llinstantmessage"></block>
  </category>

  <category name="Looks & Sound">
  </category>

  <category name="Logic">
      <block type="controls_if"></block>
      <block type="logic_compare"></block>
      <block type="logic_operation"></block>
      <block type="logic_negate"></block>
      <block type="logic_boolean"></block>
<!--       <block type="logic_null"></block> -->
      <block type="logic_ternary"></block>
    </category>

    <category name="Loops">
      <block type="controls_repeat_ext">
        <value name="TIMES">
          <block type="math_number">
            <field name="NUM">10</field>
          </block>
        </value>
      </block>
      <block type="controls_whileUntil"></block>
      <block type="controls_for">
        <value name="FROM">
          <block type="math_number">
            <field name="NUM">1</field>
          </block>
        </value>
        <value name="TO">
          <block type="math_number">
            <field name="NUM">10</field>
          </block>
        </value>
        <value name="BY">
          <block type="math_number">
            <field name="NUM">1</field>
          </block>
        </value>
      </block>
      <block type="controls_flow_statements"></block>
      <!-- <block type="controls_forEach"></block> -->
      <!-- <block type="controls_repeat"></block> -->
    </category>

    <category name="Math">
      <block type="math_number"></block>
      <block type="math_arithmetic"></block>
      <block type="math_single"></block>
      <block type="math_constant"></block>
      <category name="More">
        <block type="math_number_property"></block>
<!--         <block type="math_change"></block> -->
        <block type="math_round"></block>
        <block type="math_trig"></block>
<!--         <block type="math_on_list"></block> -->
        <block type="math_modulo"></block>
        <block type="math_constrain"></block>
        <block type="math_random_int"></block>
        <block type="math_random_float"></block>
      </category>
    </category>

    <category name="Text">
      <block type="text"></block>
      <block type="text_print">
        <value name="TEXT">
          <block type="text"></block>
        </value>
      </block>
      <block type="text_join"></block>
      <category name="More">
        <block type="text_append"></block>
        <block type="text_length"></block>
        <block type="text_isEmpty"></block>
        <block type="text_indexOf"></block>
        <block type="text_charAt"></block>
        <block type="text_getSubstring"></block>
        <block type="text_changeCase"></block>
        <block type="text_trim"></block>
<!--         <block type="text_prompt"></block> -->
      </category>
    </category>

</xml>